README.md
setup.cfg
setup.py
acmclient/__init__.py
acmclient/app.py
acmclient/const.py
acmclient/utils.py
acmclient.egg-info/PKG-INFO
acmclient.egg-info/SOURCES.txt
acmclient.egg-info/dependency_links.txt
acmclient.egg-info/requires.txt
acmclient.egg-info/top_level.txt
tests/__init__.py
tests/conftest.py
tests/test_client.py
tests/test_server_list_manager.py