Metadata-Version: 1.1
Name: acmclient
Version: 0.2
Summary: Aliyun acm client for Python
Home-page: https://github.com/yangjiaronga/acmclient/
Author: yangjiaronga
Author-email: yangjiaronga@gmail.com
License: MIT
Platform: UNKNOWN
Classifier: Environment :: Web Environment
Classifier: Intended Audience :: Developers
Classifier: Operating System :: OS Independent
Classifier: Programming Language :: Python :: 3
Classifier: Programming Language :: Python :: 3.4
Classifier: Programming Language :: Python :: 3.5
Classifier: Programming Language :: Python :: 3.6
